fyle_db_connector/__init__.py
fyle_db_connector/extract.py
fyle_db_connector/extract_ddl.sql
fyle_db_connector/load.py
fyle_db_connector/load_ddl.sql
test/__init__.py
test/common/__init__.py
test/common/utilities.py
test/integration/__init__.py
test/integration/conftest.py
test/integration/test_fyle.py
test/unit/__init__.py
test/unit/conftest.py
test/unit/test_extract.py
test/unit/test_load.py
test/unit/test_mocks.py
fyle_db_connector-0.14.0.dist-info/LICENSE
fyle_db_connector-0.14.0.dist-info/METADATA
fyle_db_connector-0.14.0.dist-info/WHEEL
fyle_db_connector-0.14.0.dist-info/top_level.txt
fyle_db_connector-0.14.0.dist-info/RECORD
