Metadata-Version: 2.1
Name: fyle-db-connector
Version: 0.14.0
Summary: Connects Fyle to a database connector to transfer information to and fro.
Home-page: https://github.com/fylein/fyle-db-connector
Author: Shwetabh Kumar
Author-email: shwetabh.kumar@fyle.in
License: MIT
Keywords: fyle,db,python,sdk,sqlite,postgres
Platform: UNKNOWN
Classifier: Topic :: Internet :: WWW/HTTP
Classifier: Intended Audience :: Developers
Classifier: Programming Language :: Python :: 3
Classifier: License :: OSI Approved :: MIT License
Classifier: Operating System :: OS Independent
Requires-Dist: pandas (==0.25.2)
Requires-Dist: fylesdk (>=1.4.0)
